helloworld/__init__.py
helloworld/main.py
helloworld_printer-1.0.1.dist-info/LICENSE
helloworld_printer-1.0.1.dist-info/METADATA
helloworld_printer-1.0.1.dist-info/WHEEL
helloworld_printer-1.0.1.dist-info/entry_points.txt
helloworld_printer-1.0.1.dist-info/top_level.txt
helloworld_printer-1.0.1.dist-info/RECORD
